punk/__init__.py
punk/aggregator/__init__.py
punk/aggregator/aggregateByCategory.py
punk/aggregator/aggregateByDateTime.py
punk/aggregator/aggregateByDateTimeCategory.py
punk/aggregator/aggregateByNumericRange.py
punk/aggregator/categorical.py
punk/aggregator/definitions.py
punk/aggregator/numeric.py
punk/aggregator/timeseries.py
punk/feature_selection/__init__.py
punk/feature_selection/pca.py
punk/feature_selection/rf.py
punk/preppy/__init__.py
punk/preppy/cleanDates.py
punk/preppy/cleanNumbers.py
punk/preppy/cleanStrings.py
punk/preppy/clean_list.py
punk/preppy/clean_value.py
punk/preppy/encoders.py
punk/preppy/format.py
punk/preppy/transform.py
punk/preppy/utils.py
punkML-3.0.1.dist-info/LICENSE
punkML-3.0.1.dist-info/METADATA
punkML-3.0.1.dist-info/WHEEL
punkML-3.0.1.dist-info/top_level.txt
punkML-3.0.1.dist-info/RECORD
